owghatapi/__init__.py
owghatapi/admin.py
owghatapi/apps.py
owghatapi/models.py
owghatapi/serializers.py
owghatapi/tests.py
owghatapi/urls.py
owghatapi/views.py
owghatapi/migrations/0001_initial.py
owghatapi/migrations/__init__.py
owghatapi/utils/PrayTimes.py
owghatapi/utils/PrayerTimeProvider.py
owghatapi/utils/__pycache__/PrayTimes.cpython-37.pyc
owghatapi/utils/__pycache__/PrayerTimeProvider.cpython-37.pyc
owghatapi/utils/sql/iran_cities_farsi.sql
django_owghatapi-0.2.2.dist-info/METADATA
django_owghatapi-0.2.2.dist-info/WHEEL
django_owghatapi-0.2.2.dist-info/top_level.txt
django_owghatapi-0.2.2.dist-info/RECORD
